jentic/apitools/openapi/validator/backends/base.py
jentic/apitools/openapi/validator/backends/default/__init__.py
jentic/apitools/openapi/validator/backends/default/rules/__init__.py
jentic/apitools/openapi/validator/backends/default/rules/security.py
jentic/apitools/openapi/validator/backends/default/rules/server.py
jentic/apitools/openapi/validator/backends/default/rules/structural.py
jentic/apitools/openapi/validator/backends/openapi_spec.py
jentic/apitools/openapi/validator/backends/py.typed
jentic/apitools/openapi/validator/core/__init__.py
jentic/apitools/openapi/validator/core/diagnostics.py
jentic/apitools/openapi/validator/core/openapi_validator.py
jentic/apitools/openapi/validator/core/py.typed
jentic_openapi_validator-1.0.0a34.dist-info/licenses/LICENSE
jentic_openapi_validator-1.0.0a34.dist-info/licenses/NOTICE
jentic_openapi_validator-1.0.0a34.dist-info/WHEEL
jentic_openapi_validator-1.0.0a34.dist-info/entry_points.txt
jentic_openapi_validator-1.0.0a34.dist-info/METADATA
jentic_openapi_validator-1.0.0a34.dist-info/RECORD
