Metadata-Version: 2.4
Name: jentic-openapi-validator
Version: 1.0.0a34
Summary: Jentic OpenAPI Validator
Author: Jentic
Author-email: Jentic <hello@jentic.com>
License-Expression: Apache-2.0
License-File: LICENSE
License-File: NOTICE
Requires-Dist: jentic-openapi-parser~=1.0.0a34
Requires-Dist: openapi-spec-validator~=0.7.2
Requires-Dist: lsprotocol~=2025.0.0
Requires-Dist: jentic-openapi-validator-redocly~=1.0.0a34 ; extra == 'redocly'
Requires-Dist: jentic-openapi-validator-spectral~=1.0.0a34 ; extra == 'spectral'
Requires-Python: >=3.11
Project-URL: Homepage, https://github.com/jentic/jentic-openapi-tools
Provides-Extra: redocly
Provides-Extra: spectral
